pbkdf2/__init__.py
pbkdf2/internals.py
pbkdf2_reboot-1.0.dist-info/METADATA
pbkdf2_reboot-1.0.dist-info/WHEEL
pbkdf2_reboot-1.0.dist-info/top_level.txt
pbkdf2_reboot-1.0.dist-info/RECORD
