Metadata-Version: 2.1
Name: pbkdf2-reboot
Version: 1.0
Summary: pbkdf2 implementation in modern python with typing support.
Home-page: UNKNOWN
Author: Sigmanificient
License: UNKNOWN
Project-URL: Github repository, https://github.com/Sigmanificient/pbkdf2-reboot
Keywords: pbkdf,pbkdf2,cryptography,hashing,password,encryption,typing
Platform: unix
Platform: linux
Platform: osx
Platform: cygwin
Platform: win32
Classifier: Programming Language :: Python :: 3
Classifier: Programming Language :: Python :: 3 :: Only
Classifier: Programming Language :: Python :: 3.8
Classifier: Programming Language :: Python :: 3.9
Classifier: Programming Language :: Python :: 3.10
Classifier: Programming Language :: Python :: 3.11
Requires-Python: >=3.8
Provides-Extra: testing
Requires-Dist: coverage (>=6.3.0) ; extra == 'testing'
Requires-Dist: codecov (>=2.0.0) ; extra == 'testing'
Requires-Dist: pytest (>=7.1.2) ; extra == 'testing'
Requires-Dist: pytest-cov (>=3.0.0) ; extra == 'testing'
Requires-Dist: mypy (>=0.950) ; extra == 'testing'
Requires-Dist: black (>=22.3.0) ; extra == 'testing'
